LICENSE
MANIFEST.in
setup.py
bin/proc_um_output
umtools/__init__.py
umtools/irismode.py
umtools/utils.py
umtools/version.py
umtools/xraymode.py
umtools.egg-info/PKG-INFO
umtools.egg-info/SOURCES.txt
umtools.egg-info/dependency_links.txt
umtools.egg-info/pbr.json
umtools.egg-info/top_level.txt
umtools/tests/__init__.py
umtools/tests/test_umtools.py