Metadata-Version: 1.1
Name: umtools
Version: 0.1.5
Summary: umtools: a Python toolbox for UK Met Office Unified Model output
Home-page: http://github.com/dennissergeev/umtools
Author: Denis Sergeev
Author-email: dennis.sergeev@gmail.com
License: MIT
Platform: UNKNOWN
Classifier: Development Status :: 3 - Alpha
Classifier: Environment :: Console
Classifier: Intended Audience :: Science/Research
Classifier: License :: OSI Approved :: MIT License
Classifier: Operating System :: POSIX :: Linux
Classifier: Programming Language :: Python
Classifier: Topic :: Scientific/Engineering :: Atmospheric Science
Requires: iris
Requires: matplotlib
Requires: netcdf4
Requires: numpy
Requires: scipy
